teras/__init__.py
teras/activations.py
teras/api_export.py
teras/data_utils.py
teras/typing.py
teras/utils.py
teras/version.py
teras/_src/__init__.py
teras/_src/activations.py
teras/_src/activations_test.py
teras/_src/api_export.py
teras/_src/data_utils.py
teras/_src/decorators.py
teras/_src/dtypes.py
teras/_src/typing.py
teras/_src/utils.py
teras/_src/utils_test.py
teras/_src/backend/__init__.py
teras/_src/backend/generic_utils.py
teras/_src/backend/wrappers.py
teras/_src/backend/common/__init__.py
teras/_src/backend/common/models/__init__.py
teras/_src/backend/common/models/autoencoders/__init__.py
teras/_src/backend/common/models/autoencoders/tvae/__init__.py
teras/_src/backend/common/models/autoencoders/tvae/tvae.py
teras/_src/backend/common/models/gans/__init__.py
teras/_src/backend/common/models/gans/gain.py
teras/_src/backend/common/models/gans/pcgain.py
teras/_src/backend/common/models/gans/ctgan/__init__.py
teras/_src/backend/common/models/gans/ctgan/ctgan.py
teras/_src/backend/common/models/gans/ctgan/discriminator.py
teras/_src/backend/common/models/gans/ctgan/generator.py
teras/_src/backend/common/models/pretrainers/__init__.py
teras/_src/backend/common/models/pretrainers/saint.py
teras/_src/backend/common/models/pretrainers/tab_transformer.py
teras/_src/backend/common/models/pretrainers/tabnet.py
teras/_src/backend/jax/__init__.py
teras/_src/backend/jax/ops.py
teras/_src/backend/jax/utils.py
teras/_src/backend/jax/models/__init__.py
teras/_src/backend/jax/models/autoencoders/__init__.py
teras/_src/backend/jax/models/autoencoders/tvae/__init__.py
teras/_src/backend/jax/models/autoencoders/tvae/tvae.py
teras/_src/backend/jax/models/gans/__init__.py
teras/_src/backend/jax/models/gans/gain.py
teras/_src/backend/jax/models/gans/gain_fit_test.py
teras/_src/backend/jax/models/gans/jaxgan.py
teras/_src/backend/jax/models/gans/pcgain.py
teras/_src/backend/jax/models/gans/pcgain_fit_test.py
teras/_src/backend/jax/models/gans/ctgan/__init__.py
Teras-0.3.1.dist-info/LICENSE
Teras-0.3.1.dist-info/METADATA
Teras-0.3.1.dist-info/WHEEL
Teras-0.3.1.dist-info/top_level.txt
Teras-0.3.1.dist-info/RECORD
