Metadata-Version: 2.1
Name: Teras
Version: 0.3.1
Summary: A Unified Deep Learning Library for Tabular Data
Author: Khawaja Abaid
Author-email: Khawaja Abaid <khawaja.abaid@gmail.com>
Project-URL: Homepage, https://github.com/KhawajaAbaid/teras
Project-URL: Bug Tracker, https://github.com/KhawajaAbaid/teras/issues
Project-URL: Docs, https://teras.readthedocs.io/
Classifier: Programming Language :: Python :: 3
Classifier: Operating System :: OS Independent
Requires-Python: >=3.9
License-File: LICENSE
